tenxer_pivotal_git_hooks
