Metadata-Version: 1.0
Name: tenxer-pivotal-git-hooks
Version: 0.1.2
Summary: Automate Pivotal usage with git hooks
Home-page: http://github.com/tenXer/tenxer_pivotal_git_hooks
Author: Brad Scheppler
Author-email: brad@tenxer.com
License: MIT
Keywords: git hook pre-commit prepare-commit-msg
Platform: UNKNOWN
